sphinxience/__init__.py
sphinxience/collapse.py
sphinxience/layout.html
sphinxience/skip.py
sphinxience/static/collapse-details-polyfill.css
sphinxience/static/collapse-details-polyfill.js
sphinxience/static/jquery.details.min.js
sphinxience/static/sphinxience.css
sphinxience/templates/sphinxience-article.cls_t
sphinxience/templates/sphinxience.sty_t
sphinxience/theme.conf
sphinxience-0.4.2.dist-info/entry_points.txt
sphinxience-0.4.2.dist-info/LICENSE
sphinxience-0.4.2.dist-info/WHEEL
sphinxience-0.4.2.dist-info/METADATA
sphinxience-0.4.2.dist-info/RECORD
